{"order_id": "330eb3ca-1f7c-11ee-bf71-00155d360ae2", "order_total": 259980, "product_info": {"product_id": "442717b5-5d88-4afd-ac59-1ebf3856b207", "product_description": "Smart TV Samsung"}, "customer_info": {"customer_id": "31cf8360-2ba8-4481-ae43-f338d054b9b3", "customer_name": "Catarina Campos", "customer_phone_number": "+55 (041) 0845-3369"}, "payment_info": {"payment_type": "credit_card", "card_number": "376875157446437", "provider": "American Express", "expire": "11/29", "security_code": "050"}, "delivery_address": {"zip_code": "73981965", "country": "Brazil", "state": "Goiás", "city": "Dias de Jesus", "street": "Viela João Gabriel Dias", "number": "42"}, "order_created_at": "2023-05-01 13:15:23"}