{"order_id": "352b4d3a-1f7c-11ee-bf71-00155d360ae2", "order_total": 34290, "product_info": {"product_id": "290d498e-a1b0-4d0a-9703-7b2ff751d672", "product_description": "HD Toshiba L200"}, "customer_info": {"customer_id": "13971fcf-666c-4735-aec2-3d4854e87a8e", "customer_name": "Dra. Laura Gonçalves", "customer_phone_number": "(031) 3865-1614"}, "payment_info": {"payment_type": "credit_card", "card_number": "5108285566280407", "provider": "Maestro", "expire": "03/30", "security_code": "936"}, "delivery_address": {"zip_code": "23151343", "country": "Brazil", "state": "Amazonas", "city": "Moraes do Norte", "street": "Pátio Campos", "number": "43"}, "order_created_at": "2023-05-02 23:42:41"}